extras/__init__.py
extras/extra_script.py
subpackage/__init__.py
subpackage/check.py
version2scripts/__init__.py
version2scripts/newscript.py
vicarispackagetest/__init__.py
vicarispackagetest/run.py
vicarispackagetest-0.2.dist-info/METADATA
vicarispackagetest-0.2.dist-info/WHEEL
vicarispackagetest-0.2.dist-info/top_level.txt
vicarispackagetest-0.2.dist-info/RECORD
